setup.py
rubixgram_client/DataParse.py
rubixgram_client/__init__.py
rubixgram_client/bootloader.py
rubixgram_client/crypto.py
rubixgram_client/horror_rubixgram.py
rubixgram_client/network.py
rubixgram_client/setup.py
rubixgram_client/updater.py
rubixgram_client.egg-info/PKG-INFO
rubixgram_client.egg-info/SOURCES.txt
rubixgram_client.egg-info/dependency_links.txt
rubixgram_client.egg-info/requires.txt
rubixgram_client.egg-info/top_level.txt