Metadata-Version: 2.1
Name: rubixgram-client
Version: 1.0.0
Summary: Rubika Asynchronous/Synchronous Client Library 
Home-page: https://github.com/Rubier-Project/RubiXgram
Author: Host1let
Author-email: sqlmapssh@gmail.com
License: MIT
Download-URL: https://github.com/Rubier-Project/RubiXgram/archive/refs/heads/main.zip
Keywords: rubx
Platform: UNKNOWN
Classifier: Development Status :: 3 - Alpha
Classifier: Intended Audience :: Developers
Classifier: Topic :: Software Development :: Build Tools
Classifier: License :: OSI Approved :: MIT License
Classifier: Programming Language :: Python :: 3
Classifier: Programming Language :: Python :: 3.8
Classifier: Programming Language :: Python :: 3.9
Classifier: Programming Language :: Python :: 3.10
Classifier: Programming Language :: Python :: 3.11
